multifile_ida_plugin/__init__.py
multifile_ida_plugin/plugin/__init__.py
multifile_ida_plugin-0.1.0.dist-info/METADATA
multifile_ida_plugin-0.1.0.dist-info/WHEEL
multifile_ida_plugin-0.1.0.dist-info/entry_points.txt
multifile_ida_plugin-0.1.0.dist-info/top_level.txt
multifile_ida_plugin-0.1.0.dist-info/RECORD
