Metadata-Version: 2.4
Name: multifile-ida-plugin
Version: 0.1.0
Summary: Example IDA Plugin with multiple files
Author-email: Willi Ballenthin <willi.ballenthin@gmail.com>
License-Expression: Apache-2.0
Requires-Python: >=3.9
